README.md
setup.py
uravo/__init__.py
uravo/config.py
uravo/uravo.py
uravo.egg-info/PKG-INFO
uravo.egg-info/SOURCES.txt
uravo.egg-info/dependency_links.txt
uravo.egg-info/requires.txt
uravo.egg-info/top_level.txt