Metadata-Version: 2.1
Name: uravo
Version: 0.0.3
Summary: Python interface to the Uravo monitoring system
Home-page: https://github.com/minorimpact/python-uravo
Author: Patrick Gillan
Author-email: pgillan@minorimpact.com
License: GPLv3
Platform: UNKNOWN
